[{"id":1,"first_name":"Dick","last_name":"Sweetsur","email":"dsweetsur0@diigo.com","date_of_birth":"1970-10-17T14:41:19Z","age":58,"country":"Indonesia","phone":"3108315111"},
{"id":2,"first_name":"Lark","last_name":"McIlmurray","email":"lmcilmurray1@google.it","date_of_birth":"1975-04-20T05:56:50Z","age":27,"country":"China","phone":"1858352157"},
{"id":3,"first_name":"Jonathon","last_name":"Bassano","email":"jbassano2@sourceforge.net","date_of_birth":"1983-01-22T04:28:00Z","age":56,"country":"Albania","phone":"1121637122"},
{"id":4,"first_name":"Ophelie","last_name":"Lutas","email":"olutas3@hp.com","date_of_birth":"1996-07-24T20:46:40Z","age":54,"country":"United States","phone":"2143625478"},
{"id":5,"first_name":"Dorry","last_name":"Andren","email":"dandren4@nhs.uk","date_of_birth":"2018-09-27T06:43:43Z","age":72,"country":"China","phone":"2024311687"},
{"id":6,"first_name":"Kipp","last_name":"Forgan","email":"kforgan5@gnu.org","date_of_birth":"2009-02-11T16:09:35Z","age":37,"country":"China","phone":"6152830602"},
{"id":7,"first_name":"Uriel","last_name":"Ortell","email":"uortell6@merriam-webster.com","date_of_birth":"2015-05-31T00:57:31Z","age":40,"country":"Finland","phone":"1256159560"},
{"id":8,"first_name":"Travus","last_name":"Roblou","email":"troblou7@theguardian.com","date_of_birth":"2010-04-28T15:14:00Z","age":37,"country":"Poland","phone":"5087891616"},
{"id":9,"first_name":"Emanuel","last_name":"Plose","email":"eplose8@lulu.com","date_of_birth":"1992-09-24T00:58:44Z","age":21,"country":"Russia","phone":"2006625009"},
{"id":10,"first_name":"Humfrey","last_name":"Syms","email":"hsyms9@businessweek.com","date_of_birth":"2004-08-15T17:35:52Z","age":30,"country":"Syria","phone":"1897582639"},
{"id":11,"first_name":"Wyatt","last_name":"O'Brallaghan","email":"wobrallaghana@tinypic.com","date_of_birth":"1971-05-04T00:49:49Z","age":53,"country":"Bangladesh","phone":"4855171929"},
{"id":12,"first_name":"Tarrance","last_name":"D'Aeth","email":"tdaethb@alibaba.com","date_of_birth":"2021-11-20T07:57:39Z","age":67,"country":"China","phone":"9411656788"},
{"id":13,"first_name":"Gilly","last_name":"Dunkerly","email":"gdunkerlyc@yellowpages.com","date_of_birth":"2022-09-16T18:59:16Z","age":39,"country":"Russia","phone":"4936600531"},
{"id":14,"first_name":"Ilka","last_name":"Caulier","email":"icaulierd@dell.com","date_of_birth":"1999-07-11T04:17:10Z","age":75,"country":"Canada","phone":"6846187502"},
{"id":15,"first_name":"Gabi","last_name":"O'Loghlen","email":"gologhlene@free.fr","date_of_birth":"1989-03-27T22:58:26Z","age":37,"country":"China","phone":"1792884682"},
{"id":16,"first_name":"Corabel","last_name":"Mulheron","email":"cmulheronf@oakley.com","date_of_birth":"2014-03-22T21:09:12Z","age":74,"country":"Dominican Republic","phone":"6008488831"},
{"id":17,"first_name":"Antoni","last_name":"Stutard","email":"astutardg@cdc.gov","date_of_birth":"2021-03-15T18:33:17Z","age":38,"country":"Indonesia","phone":"2224785340"},
{"id":18,"first_name":"Aldric","last_name":"Darling","email":"adarlingh@mapquest.com","date_of_birth":"2006-12-16T07:42:58Z","age":29,"country":"Yemen","phone":"2729928348"},
{"id":19,"first_name":"Ketti","last_name":"Dennett","email":"kdennetti@hp.com","date_of_birth":"2010-06-24T19:57:53Z","age":66,"country":"Indonesia","phone":"3521861736"},
{"id":20,"first_name":"Di","last_name":"Igonet","email":"digonetj@fda.gov","date_of_birth":"2014-09-28T17:48:39Z","age":29,"country":"Azerbaijan","phone":"4667649362"},
{"id":21,"first_name":"Brittne","last_name":"Thorold","email":"bthoroldk@cocolog-nifty.com","date_of_birth":"2010-12-18T00:13:38Z","age":33,"country":"Sweden","phone":"9124035583"},
{"id":22,"first_name":"Dre","last_name":"Mashro","email":"dmashrol@go.com","date_of_birth":"1990-06-17T07:47:50Z","age":67,"country":"Russia","phone":"8224070425"},
{"id":23,"first_name":"Ody","last_name":"Pulsford","email":"opulsfordm@google.pl","date_of_birth":"1990-11-22T20:48:44Z","age":63,"country":"Brazil","phone":"6029441387"},
{"id":24,"first_name":"Ddene","last_name":"Shilburne","email":"dshilburnen@purevolume.com","date_of_birth":"1973-10-01T03:47:16Z","age":53,"country":"Indonesia","phone":"7517107285"},
{"id":25,"first_name":"Marge","last_name":"Smullen","email":"msmulleno@cmu.edu","date_of_birth":"2002-06-30T06:06:32Z","age":54,"country":"China","phone":"6844142341"},
{"id":26,"first_name":"Ivory","last_name":"Arnoll","email":"iarnollp@nifty.com","date_of_birth":"1979-11-07T19:21:13Z","age":22,"country":"Indonesia","phone":"4397199409"},
{"id":27,"first_name":"Eberto","last_name":"Manolov","email":"emanolovq@twitter.com","date_of_birth":"2004-10-15T18:26:50Z","age":54,"country":"Philippines","phone":"7999025898"},
{"id":28,"first_name":"Ashlen","last_name":"Crumpton","email":"acrumptonr@discovery.com","date_of_birth":"2021-05-02T00:21:30Z","age":33,"country":"Indonesia","phone":"4992052821"},
{"id":29,"first_name":"Ferdinanda","last_name":"Kenlin","email":"fkenlins@bluehost.com","date_of_birth":"1972-07-11T12:54:49Z","age":76,"country":"China","phone":"2869773557"},
{"id":30,"first_name":"Gearard","last_name":"Steffens","email":"gsteffenst@canalblog.com","date_of_birth":"1972-08-08T10:07:55Z","age":58,"country":"China","phone":"1393197402"},
{"id":31,"first_name":"Maighdiln","last_name":"Vondra","email":"mvondrau@google.com","date_of_birth":"1972-05-25T04:57:10Z","age":70,"country":"Poland","phone":"4732259512"},
{"id":32,"first_name":"Myrah","last_name":"Chasmor","email":"mchasmorv@about.me","date_of_birth":"2009-01-15T20:40:01Z","age":60,"country":"Nepal","phone":"8644274474"},
{"id":33,"first_name":"Carla","last_name":"Hancill","email":"chancillw@multiply.com","date_of_birth":"2008-07-28T20:12:14Z","age":47,"country":"France","phone":"9473989745"},
{"id":34,"first_name":"Karalynn","last_name":"Renals","email":"krenalsx@flavors.me","date_of_birth":"1994-04-26T22:34:59Z","age":53,"country":"France","phone":"9244458837"},
{"id":35,"first_name":"Thomasin","last_name":"Smoughton","email":"tsmoughtony@networkadvertising.org","date_of_birth":"2017-02-03T10:55:26Z","age":73,"country":"Czech Republic","phone":"9527568734"},
{"id":36,"first_name":"Rurik","last_name":"Normand","email":"rnormandz@google.com.br","date_of_birth":"1971-01-19T12:05:08Z","age":74,"country":"Indonesia","phone":"4789088229"},
{"id":37,"first_name":"Davina","last_name":"Jouannot","email":"djouannot10@hostgator.com","date_of_birth":"1982-01-22T12:52:20Z","age":47,"country":"Indonesia","phone":"8358604013"},
{"id":38,"first_name":"Alphonse","last_name":"Buzine","email":"abuzine11@answers.com","date_of_birth":"1975-12-23T12:14:03Z","age":20,"country":"China","phone":"9239619485"},
{"id":39,"first_name":"Caryl","last_name":"Curtiss","email":"ccurtiss12@weather.com","date_of_birth":"1994-05-28T02:26:52Z","age":65,"country":"Russia","phone":"1349633598"},
{"id":40,"first_name":"Brandais","last_name":"Devin","email":"bdevin13@bbb.org","date_of_birth":"1972-05-25T18:17:53Z","age":50,"country":"China","phone":"7402390538"},
{"id":41,"first_name":"Jourdain","last_name":"Peers","email":"jpeers14@answers.com","date_of_birth":"2020-10-28T00:12:31Z","age":26,"country":"Morocco","phone":"2995914238"},
{"id":42,"first_name":"Legra","last_name":"Kirkup","email":"lkirkup15@homestead.com","date_of_birth":"1976-03-23T20:31:08Z","age":69,"country":"Nigeria","phone":"9086141121"},
{"id":43,"first_name":"Fransisco","last_name":"Crammy","email":"fcrammy16@mac.com","date_of_birth":"1987-07-07T05:18:18Z","age":73,"country":"Argentina","phone":"3192750947"},
{"id":44,"first_name":"Gregoire","last_name":"Maude","email":"gmaude17@omniture.com","date_of_birth":"2000-09-24T03:49:00Z","age":47,"country":"Morocco","phone":"1033251040"},
{"id":45,"first_name":"Homerus","last_name":"Bryer","email":"hbryer18@usgs.gov","date_of_birth":"2017-09-15T18:48:17Z","age":47,"country":"Philippines","phone":"2189693322"},
{"id":46,"first_name":"Tobe","last_name":"Berre","email":"tberre19@live.com","date_of_birth":"2000-10-01T22:50:42Z","age":51,"country":"Philippines","phone":"8012474618"},
{"id":47,"first_name":"Manolo","last_name":"Rizzotto","email":"mrizzotto1a@jigsy.com","date_of_birth":"2007-04-16T20:32:05Z","age":19,"country":"Portugal","phone":"8542862176"},
{"id":48,"first_name":"Thelma","last_name":"Bettaney","email":"tbettaney1b@surveymonkey.com","date_of_birth":"2001-04-14T04:19:36Z","age":19,"country":"Russia","phone":"4497292502"},
{"id":49,"first_name":"Erastus","last_name":"Pughsley","email":"epughsley1c@narod.ru","date_of_birth":"1981-06-27T12:48:57Z","age":75,"country":"China","phone":"6177325770"},
{"id":50,"first_name":"Augustine","last_name":"Charman","email":"acharman1d@ucoz.com","date_of_birth":"1982-03-10T16:45:07Z","age":19,"country":"Thailand","phone":"3657314331"},
{"id":51,"first_name":"Marsh","last_name":"Joerning","email":"mjoerning1e@phpbb.com","date_of_birth":"1997-10-02T09:46:56Z","age":41,"country":"Philippines","phone":"2331928467"},
{"id":52,"first_name":"Alisa","last_name":"Fassbender","email":"afassbender1f@cloudflare.com","date_of_birth":"2011-04-10T14:56:10Z","age":31,"country":"Philippines","phone":"8335406250"},
{"id":53,"first_name":"Ty","last_name":"O'Kennavain","email":"tokennavain1g@list-manage.com","date_of_birth":"1998-02-04T05:38:49Z","age":64,"country":"Indonesia","phone":"2494326365"},
{"id":54,"first_name":"Aigneis","last_name":"Sawford","email":"asawford1h@github.com","date_of_birth":"1996-09-12T23:00:32Z","age":68,"country":"Yemen","phone":"6737423425"},
{"id":55,"first_name":"Hunt","last_name":"Rubert","email":"hrubert1i@vinaora.com","date_of_birth":"1982-05-02T00:19:25Z","age":60,"country":"Germany","phone":"9528141437"},
{"id":56,"first_name":"Bennett","last_name":"Lambarton","email":"blambarton1j@usa.gov","date_of_birth":"1999-10-25T12:13:26Z","age":55,"country":"Sweden","phone":"4803167205"},
{"id":57,"first_name":"Bing","last_name":"Mowson","email":"bmowson1k@ycombinator.com","date_of_birth":"2002-01-10T07:31:07Z","age":32,"country":"China","phone":"9502328937"},
{"id":58,"first_name":"Maurise","last_name":"Huddleston","email":"mhuddleston1l@soup.io","date_of_birth":"1980-08-02T06:42:10Z","age":63,"country":"China","phone":"1461692691"},
{"id":59,"first_name":"Barbe","last_name":"Athowe","email":"bathowe1m@senate.gov","date_of_birth":"2008-08-28T06:00:14Z","age":36,"country":"Iran","phone":"2821369044"},
{"id":60,"first_name":"Jan","last_name":"Krysztowczyk","email":"jkrysztowczyk1n@blinklist.com","date_of_birth":"1999-09-30T19:18:22Z","age":31,"country":"Russia","phone":"1788261858"},
{"id":61,"first_name":"Ave","last_name":"Beadles","email":"abeadles1o@gravatar.com","date_of_birth":"1999-01-30T15:45:11Z","age":38,"country":"Portugal","phone":"4336699088"},
{"id":62,"first_name":"Sauncho","last_name":"Conquest","email":"sconquest1p@businesswire.com","date_of_birth":"1992-08-25T01:28:48Z","age":62,"country":"United Kingdom","phone":"1401014797"},
{"id":63,"first_name":"Marice","last_name":"Waplington","email":"mwaplington1q@cloudflare.com","date_of_birth":"1970-12-30T18:04:13Z","age":55,"country":"France","phone":"2709078741"},
{"id":64,"first_name":"Cointon","last_name":"Nelm","email":"cnelm1r@google.cn","date_of_birth":"1983-05-31T04:47:04Z","age":31,"country":"Canada","phone":"1485135793"},
{"id":65,"first_name":"Clotilda","last_name":"Beretta","email":"cberetta1s@oakley.com","date_of_birth":"1990-06-10T11:30:14Z","age":76,"country":"Jordan","phone":"6457309218"},
{"id":66,"first_name":"Lilla","last_name":"Hawthorne","email":"lhawthorne1t@youku.com","date_of_birth":"1983-11-15T16:12:48Z","age":43,"country":"Nauru","phone":"5899807953"},
{"id":67,"first_name":"Wilona","last_name":"McGrorty","email":"wmcgrorty1u@plala.or.jp","date_of_birth":"2016-06-04T20:46:24Z","age":23,"country":"Oman","phone":"7783359932"},
{"id":68,"first_name":"Donny","last_name":"Desson","email":"ddesson1v@paypal.com","date_of_birth":"1993-06-29T22:28:49Z","age":61,"country":"Serbia","phone":"5691378216"},
{"id":69,"first_name":"Zonda","last_name":"Geaney","email":"zgeaney1w@cdc.gov","date_of_birth":"2014-12-04T23:46:07Z","age":31,"country":"Brazil","phone":"5926799084"},
{"id":70,"first_name":"Asa","last_name":"Clace","email":"aclace1x@wordpress.org","date_of_birth":"1974-05-05T01:57:39Z","age":20,"country":"United States","phone":"8599456028"},
{"id":71,"first_name":"Marion","last_name":"Stidever","email":"mstidever1y@bloomberg.com","date_of_birth":"1975-07-24T08:03:17Z","age":45,"country":"Morocco","phone":"6695358788"},
{"id":72,"first_name":"Finn","last_name":"Millberg","email":"fmillberg1z@zdnet.com","date_of_birth":"1988-09-03T23:24:58Z","age":31,"country":"Portugal","phone":"6236028049"},
{"id":73,"first_name":"Venus","last_name":"Crich","email":"vcrich20@hhs.gov","date_of_birth":"2006-10-09T23:37:32Z","age":32,"country":"Philippines","phone":"2907161967"},
{"id":74,"first_name":"Sean","last_name":"Sancias","email":"ssancias21@wiley.com","date_of_birth":"1996-05-02T11:03:32Z","age":19,"country":"Israel","phone":"4099817071"},
{"id":75,"first_name":"Greggory","last_name":"Stapells","email":"gstapells22@mozilla.com","date_of_birth":"1974-05-15T09:30:22Z","age":73,"country":"Indonesia","phone":"5406132697"},
{"id":76,"first_name":"Seward","last_name":"Mayhow","email":"smayhow23@omniture.com","date_of_birth":"1989-04-19T03:57:19Z","age":54,"country":"Mauritius","phone":"2197168225"},
{"id":77,"first_name":"Aubrette","last_name":"D'Elia","email":"adelia24@digg.com","date_of_birth":"1986-09-11T02:45:56Z","age":52,"country":"China","phone":"8755436377"},
{"id":78,"first_name":"Myrle","last_name":"McConway","email":"mmcconway25@deliciousdays.com","date_of_birth":"1983-10-20T08:12:58Z","age":41,"country":"Poland","phone":"1838691416"},
{"id":79,"first_name":"Jamil","last_name":"Gidney","email":"jgidney26@addtoany.com","date_of_birth":"2021-11-14T19:18:10Z","age":75,"country":"El Salvador","phone":"5601834521"},
{"id":80,"first_name":"Giorgia","last_name":"Facer","email":"gfacer27@cpanel.net","date_of_birth":"1979-04-15T02:39:57Z","age":46,"country":"Indonesia","phone":"4953723721"},
{"id":81,"first_name":"Lissi","last_name":"Ife","email":"life28@wunderground.com","date_of_birth":"2004-02-22T16:23:25Z","age":45,"country":"Indonesia","phone":"3862566047"},
{"id":82,"first_name":"Chanda","last_name":"Cunnell","email":"ccunnell29@addthis.com","date_of_birth":"2021-11-14T19:45:46Z","age":30,"country":"China","phone":"5435726320"},
{"id":83,"first_name":"Lazare","last_name":"Fey","email":"lfey2a@hhs.gov","date_of_birth":"2003-04-24T02:18:46Z","age":59,"country":"Iran","phone":"2313615232"},
{"id":84,"first_name":"Hinda","last_name":"Cheyney","email":"hcheyney2b@sciencedaily.com","date_of_birth":"1999-01-14T14:45:19Z","age":40,"country":"Vietnam","phone":"2047552830"},
{"id":85,"first_name":"Marybeth","last_name":"Cutmare","email":"mcutmare2c@wisc.edu","date_of_birth":"2013-02-18T07:47:42Z","age":42,"country":"Malaysia","phone":"9132436810"},
{"id":86,"first_name":"Andie","last_name":"Farlowe","email":"afarlowe2d@cargocollective.com","date_of_birth":"1990-09-06T08:15:49Z","age":68,"country":"Bolivia","phone":"5608133224"},
{"id":87,"first_name":"Ofella","last_name":"Worstall","email":"oworstall2e@photobucket.com","date_of_birth":"2010-10-25T17:25:17Z","age":60,"country":"Indonesia","phone":"4614202385"},
{"id":88,"first_name":"Byrann","last_name":"Pentecost","email":"bpentecost2f@blogger.com","date_of_birth":"2005-02-26T13:09:57Z","age":44,"country":"France","phone":"7984037024"},
{"id":89,"first_name":"Aleen","last_name":"Scocroft","email":"ascocroft2g@hibu.com","date_of_birth":"2021-05-17T09:10:20Z","age":49,"country":"Philippines","phone":"7647791592"},
{"id":90,"first_name":"Farlay","last_name":"Colkett","email":"fcolkett2h@devhub.com","date_of_birth":"2007-12-17T12:33:54Z","age":25,"country":"Kazakhstan","phone":"2786501429"},
{"id":91,"first_name":"Isobel","last_name":"Getty","email":"igetty2i@boston.com","date_of_birth":"1981-10-13T15:29:43Z","age":75,"country":"Indonesia","phone":"3663292129"},
{"id":92,"first_name":"Sasha","last_name":"Pass","email":"spass2j@tripadvisor.com","date_of_birth":"2017-03-15T02:05:52Z","age":59,"country":"Indonesia","phone":"7935988568"},
{"id":93,"first_name":"Roslyn","last_name":"Stoak","email":"rstoak2k@ft.com","date_of_birth":"2002-09-14T02:36:38Z","age":65,"country":"China","phone":"2017457495"},
{"id":94,"first_name":"Matti","last_name":"Stovold","email":"mstovold2l@nyu.edu","date_of_birth":"1990-02-03T21:15:21Z","age":61,"country":"Poland","phone":"6714183880"},
{"id":95,"first_name":"Philly","last_name":"Langwade","email":"plangwade2m@oakley.com","date_of_birth":"2001-11-25T20:14:07Z","age":40,"country":"Uzbekistan","phone":"5117611610"},
{"id":96,"first_name":"Tessy","last_name":"Deignan","email":"tdeignan2n@mapquest.com","date_of_birth":"2000-03-20T11:46:49Z","age":27,"country":"China","phone":"1311084374"},
{"id":97,"first_name":"Arty","last_name":"Woodgate","email":"awoodgate2o@upenn.edu","date_of_birth":"1982-10-14T17:51:56Z","age":21,"country":"China","phone":"2018744531"},
{"id":98,"first_name":"Wynn","last_name":"Caistor","email":"wcaistor2p@fotki.com","date_of_birth":"2016-01-31T13:44:37Z","age":31,"country":"Poland","phone":"5788988131"},
{"id":99,"first_name":"Kerri","last_name":"Baiden","email":"kbaiden2q@edublogs.org","date_of_birth":"2016-03-20T09:04:33Z","age":78,"country":"Philippines","phone":"5228285965"},
{"id":100,"first_name":"Siouxie","last_name":"Zaniolo","email":"szaniolo2r@jalbum.net","date_of_birth":"1990-09-10T18:26:12Z","age":25,"country":"China","phone":"6064950488"},
{"id":101,"first_name":"Delphinia","last_name":"Rousell","email":"drousell2s@addtoany.com","date_of_birth":"1979-06-07T14:34:44Z","age":68,"country":"Russia","phone":"1623954162"},
{"id":102,"first_name":"Saraann","last_name":"Seath","email":"sseath2t@cocolog-nifty.com","date_of_birth":"1982-09-18T01:22:04Z","age":24,"country":"Nigeria","phone":"8142262806"},
{"id":103,"first_name":"Maison","last_name":"Mance","email":"mmance2u@youku.com","date_of_birth":"1999-05-05T22:13:19Z","age":26,"country":"China","phone":"1089063767"},
{"id":104,"first_name":"Lorinda","last_name":"Gillbe","email":"lgillbe2v@devhub.com","date_of_birth":"2004-08-11T16:10:45Z","age":69,"country":"France","phone":"2576961518"},
{"id":105,"first_name":"Balduin","last_name":"Ivancevic","email":"bivancevic2w@europa.eu","date_of_birth":"2004-04-06T11:31:21Z","age":71,"country":"Greece","phone":"3701973600"},
{"id":106,"first_name":"Cecilia","last_name":"Kalinovich","email":"ckalinovich2x@i2i.jp","date_of_birth":"1995-01-17T18:23:57Z","age":74,"country":"France","phone":"2168536120"},
{"id":107,"first_name":"Glory","last_name":"Domelaw","email":"gdomelaw2y@bigcartel.com","date_of_birth":"1974-07-25T21:03:49Z","age":48,"country":"Bosnia and Herzegovina","phone":"5505924426"},
{"id":108,"first_name":"Michelina","last_name":"McGinnis","email":"mmcginnis2z@theguardian.com","date_of_birth":"2010-08-04T14:04:04Z","age":58,"country":"China","phone":"3288057752"},
{"id":109,"first_name":"Darelle","last_name":"Agglione","email":"dagglione30@ucoz.com","date_of_birth":"2010-05-20T19:33:29Z","age":51,"country":"Indonesia","phone":"7004416769"},
{"id":110,"first_name":"Hamlin","last_name":"Dumphry","email":"hdumphry31@usatoday.com","date_of_birth":"2002-08-30T08:08:01Z","age":67,"country":"Brazil","phone":"1521978300"},
{"id":111,"first_name":"Fernandina","last_name":"Gracewood","email":"fgracewood32@devhub.com","date_of_birth":"1977-05-10T03:10:55Z","age":76,"country":"China","phone":"4597799059"},
{"id":112,"first_name":"Davis","last_name":"Shepard","email":"dshepard33@google.ru","date_of_birth":"2002-02-11T18:01:22Z","age":33,"country":"China","phone":"6563093035"},
{"id":113,"first_name":"Curtis","last_name":"Meggison","email":"cmeggison34@nyu.edu","date_of_birth":"2014-07-19T15:46:29Z","age":48,"country":"Sweden","phone":"9761277791"},
{"id":114,"first_name":"Cornelius","last_name":"Squirrell","email":"csquirrell35@wp.com","date_of_birth":"2002-07-24T15:30:21Z","age":71,"country":"Iran","phone":"6698944997"},
{"id":115,"first_name":"Nariko","last_name":"Quenby","email":"nquenby36@statcounter.com","date_of_birth":"1986-03-24T10:43:22Z","age":48,"country":"China","phone":"1925726797"},
{"id":116,"first_name":"Ramsey","last_name":"Skeech","email":"rskeech37@prnewswire.com","date_of_birth":"1977-01-09T18:02:47Z","age":32,"country":"China","phone":"4978079338"},
{"id":117,"first_name":"Honoria","last_name":"Dawber","email":"hdawber38@ucsd.edu","date_of_birth":"1985-12-15T16:02:39Z","age":27,"country":"Ivory Coast","phone":"4688205101"},
{"id":118,"first_name":"Peyter","last_name":"Pieters","email":"ppieters39@blog.com","date_of_birth":"2023-02-15T10:40:25Z","age":39,"country":"China","phone":"8289437551"},
{"id":119,"first_name":"Ibbie","last_name":"Fogt","email":"ifogt3a@ocn.ne.jp","date_of_birth":"1999-07-24T13:05:49Z","age":38,"country":"Vietnam","phone":"2971244709"},
{"id":120,"first_name":"Nichol","last_name":"Dils","email":"ndils3b@state.gov","date_of_birth":"1975-12-08T15:30:51Z","age":36,"country":"China","phone":"8094456367"},
{"id":121,"first_name":"Marin","last_name":"Drewell","email":"mdrewell3c@statcounter.com","date_of_birth":"2022-12-18T11:45:31Z","age":32,"country":"New Zealand","phone":"4283331523"},
{"id":122,"first_name":"Aleta","last_name":"Clutterbuck","email":"aclutterbuck3d@dagondesign.com","date_of_birth":"2006-10-14T10:53:18Z","age":76,"country":"Egypt","phone":"1173059946"},
{"id":123,"first_name":"Sumner","last_name":"McDuff","email":"smcduff3e@time.com","date_of_birth":"1999-07-08T21:37:17Z","age":50,"country":"Spain","phone":"5906671544"},
{"id":124,"first_name":"Marline","last_name":"Szanto","email":"mszanto3f@phpbb.com","date_of_birth":"2014-10-19T20:36:05Z","age":41,"country":"China","phone":"7338052635"},
{"id":125,"first_name":"Aline","last_name":"Ceeley","email":"aceeley3g@unc.edu","date_of_birth":"2005-03-22T22:22:58Z","age":35,"country":"Indonesia","phone":"8059272552"},
{"id":126,"first_name":"Aubrey","last_name":"Turrill","email":"aturrill3h@cbc.ca","date_of_birth":"2013-04-09T02:07:35Z","age":68,"country":"France","phone":"3094886096"},
{"id":127,"first_name":"Ruby","last_name":"Goodinge","email":"rgoodinge3i@ocn.ne.jp","date_of_birth":"2004-02-09T09:38:12Z","age":77,"country":"Nigeria","phone":"5416916311"},
{"id":128,"first_name":"Drake","last_name":"Farquar","email":"dfarquar3j@amazon.com","date_of_birth":"2000-04-23T15:31:32Z","age":61,"country":"Saudi Arabia","phone":"9038678886"},
{"id":129,"first_name":"Elonore","last_name":"Jurn","email":"ejurn3k@yellowpages.com","date_of_birth":"1992-03-27T21:00:01Z","age":20,"country":"Sweden","phone":"4584222865"},
{"id":130,"first_name":"Bili","last_name":"Haggerstone","email":"bhaggerstone3l@odnoklassniki.ru","date_of_birth":"1998-09-11T15:31:03Z","age":44,"country":"Brazil","phone":"4089422419"},
{"id":131,"first_name":"Beret","last_name":"Clyne","email":"bclyne3m@bbc.co.uk","date_of_birth":"1990-12-05T01:19:42Z","age":31,"country":"Poland","phone":"7348234516"},
{"id":132,"first_name":"Gus","last_name":"Kulas","email":"gkulas3n@soup.io","date_of_birth":"2020-04-11T01:44:14Z","age":48,"country":"Philippines","phone":"8086232262"},
{"id":133,"first_name":"Terence","last_name":"Grzelak","email":"tgrzelak3o@dmoz.org","date_of_birth":"1973-01-21T14:02:41Z","age":57,"country":"Honduras","phone":"3618605000"},
{"id":134,"first_name":"Sayre","last_name":"Pagett","email":"spagett3p@taobao.com","date_of_birth":"1971-09-03T19:54:35Z","age":61,"country":"Argentina","phone":"2752074850"},
{"id":135,"first_name":"Christie","last_name":"Danser","email":"cdanser3q@over-blog.com","date_of_birth":"1985-12-19T02:16:54Z","age":61,"country":"Jordan","phone":"8614449990"},
{"id":136,"first_name":"Royce","last_name":"Leakner","email":"rleakner3r@hao123.com","date_of_birth":"2014-05-20T08:54:30Z","age":54,"country":"Philippines","phone":"4507855271"},
{"id":137,"first_name":"Stavros","last_name":"Mc Ilory","email":"smcilory3s@e-recht24.de","date_of_birth":"2000-10-10T01:14:18Z","age":26,"country":"Japan","phone":"1781405571"},
{"id":138,"first_name":"Carlyn","last_name":"Girauld","email":"cgirauld3t@noaa.gov","date_of_birth":"2012-01-20T21:21:01Z","age":45,"country":"Indonesia","phone":"4453962377"},
{"id":139,"first_name":"Codee","last_name":"O'Skehan","email":"coskehan3u@wunderground.com","date_of_birth":"1972-11-24T19:14:05Z","age":73,"country":"Canada","phone":"6955862901"},
{"id":140,"first_name":"Averyl","last_name":"Pickford","email":"apickford3v@sina.com.cn","date_of_birth":"1972-06-02T07:30:15Z","age":36,"country":"Albania","phone":"4545000546"},
{"id":141,"first_name":"Bendicty","last_name":"Pawelke","email":"bpawelke3w@hud.gov","date_of_birth":"2002-04-28T06:29:20Z","age":65,"country":"China","phone":"4832595833"},
{"id":142,"first_name":"Stephannie","last_name":"Smallpiece","email":"ssmallpiece3x@google.ru","date_of_birth":"1990-01-27T15:22:26Z","age":63,"country":"Bosnia and Herzegovina","phone":"6666097429"},
{"id":143,"first_name":"Tim","last_name":"Sweedy","email":"tsweedy3y@istockphoto.com","date_of_birth":"2014-01-28T15:04:50Z","age":47,"country":"Nepal","phone":"7614020542"},
{"id":144,"first_name":"Ravi","last_name":"Copping","email":"rcopping3z@ca.gov","date_of_birth":"2011-07-12T16:59:19Z","age":47,"country":"Canada","phone":"4946401465"},
{"id":145,"first_name":"Milty","last_name":"Ashling","email":"mashling40@sfgate.com","date_of_birth":"1985-07-19T22:54:41Z","age":46,"country":"France","phone":"8735318249"},
{"id":146,"first_name":"Jennilee","last_name":"Hodge","email":"jhodge41@blinklist.com","date_of_birth":"2015-04-29T07:46:34Z","age":69,"country":"Indonesia","phone":"5704604836"},
{"id":147,"first_name":"Jen","last_name":"O'Cannovane","email":"jocannovane42@intel.com","date_of_birth":"2022-01-30T03:24:33Z","age":48,"country":"Indonesia","phone":"8133648909"},
{"id":148,"first_name":"Phil","last_name":"Skey","email":"pskey43@parallels.com","date_of_birth":"1989-01-24T15:01:59Z","age":62,"country":"Brazil","phone":"7847022939"},
{"id":149,"first_name":"Darbee","last_name":"Luxford","email":"dluxford44@chicagotribune.com","date_of_birth":"1996-02-08T20:35:43Z","age":25,"country":"China","phone":"7993625849"},
{"id":150,"first_name":"Sylvan","last_name":"Vasyutkin","email":"svasyutkin45@mit.edu","date_of_birth":"2004-09-23T21:30:14Z","age":51,"country":"China","phone":"8263740054"},
{"id":151,"first_name":"Jaclin","last_name":"Ollett","email":"jollett46@discuz.net","date_of_birth":"1982-12-26T08:22:45Z","age":66,"country":"Canada","phone":"7322247209"},
{"id":152,"first_name":"Lilia","last_name":"MacTerrelly","email":"lmacterrelly47@miitbeian.gov.cn","date_of_birth":"2000-05-01T23:18:47Z","age":65,"country":"Portugal","phone":"6124065640"},
{"id":153,"first_name":"Kamilah","last_name":"Filgate","email":"kfilgate48@pagesperso-orange.fr","date_of_birth":"1977-12-07T07:38:47Z","age":60,"country":"Kazakhstan","phone":"7845773458"},
{"id":154,"first_name":"Ania","last_name":"Trustram","email":"atrustram49@nsw.gov.au","date_of_birth":"1982-06-18T11:29:21Z","age":31,"country":"Czech Republic","phone":"5176837962"},
{"id":155,"first_name":"Kerk","last_name":"Tipple","email":"ktipple4a@amazonaws.com","date_of_birth":"1971-10-28T09:48:15Z","age":19,"country":"Argentina","phone":"1099949187"},
{"id":156,"first_name":"Willi","last_name":"Alleway","email":"walleway4b@intel.com","date_of_birth":"2015-01-13T14:30:15Z","age":27,"country":"Ukraine","phone":"2106211338"},
{"id":157,"first_name":"Bird","last_name":"McChruiter","email":"bmcchruiter4c@china.com.cn","date_of_birth":"2004-06-21T23:21:32Z","age":77,"country":"Cameroon","phone":"7052951739"},
{"id":158,"first_name":"Idalina","last_name":"Yeldon","email":"iyeldon4d@fotki.com","date_of_birth":"2003-12-09T11:30:29Z","age":69,"country":"Indonesia","phone":"8044238830"},
{"id":159,"first_name":"Alec","last_name":"Dugget","email":"adugget4e@surveymonkey.com","date_of_birth":"2020-08-08T12:49:14Z","age":67,"country":"China","phone":"6057839598"},
{"id":160,"first_name":"Lin","last_name":"Bartolic","email":"lbartolic4f@upenn.edu","date_of_birth":"1979-04-27T20:51:53Z","age":30,"country":"China","phone":"3445901802"},
{"id":161,"first_name":"Babita","last_name":"Meffen","email":"bmeffen4g@bandcamp.com","date_of_birth":"1972-01-27T05:09:01Z","age":43,"country":"Yemen","phone":"1974581272"},
{"id":162,"first_name":"Dorrie","last_name":"Ossipenko","email":"dossipenko4h@hibu.com","date_of_birth":"2016-12-22T00:15:28Z","age":67,"country":"China","phone":"4956723144"},
{"id":163,"first_name":"Maurita","last_name":"Storer","email":"mstorer4i@blinklist.com","date_of_birth":"2009-01-30T01:34:52Z","age":40,"country":"Macedonia","phone":"4459928723"},
{"id":164,"first_name":"Hertha","last_name":"Cormode","email":"hcormode4j@soundcloud.com","date_of_birth":"2005-06-03T08:22:47Z","age":31,"country":"Poland","phone":"3469311576"},
{"id":165,"first_name":"Sibeal","last_name":"Dartnall","email":"sdartnall4k@freewebs.com","date_of_birth":"2014-08-12T09:29:07Z","age":66,"country":"Brazil","phone":"3484390072"},
{"id":166,"first_name":"Seline","last_name":"Balharry","email":"sbalharry4l@jiathis.com","date_of_birth":"1981-05-18T16:48:50Z","age":73,"country":"China","phone":"2541371727"},
{"id":167,"first_name":"Tedmund","last_name":"Benedito","email":"tbenedito4m@bloglines.com","date_of_birth":"1995-11-27T23:23:58Z","age":41,"country":"Canada","phone":"5188738379"},
{"id":168,"first_name":"Oona","last_name":"Armal","email":"oarmal4n@cafepress.com","date_of_birth":"1975-11-07T06:02:27Z","age":67,"country":"Poland","phone":"8196759514"},
{"id":169,"first_name":"Dietrich","last_name":"Spurdens","email":"dspurdens4o@jigsy.com","date_of_birth":"2010-09-29T13:22:53Z","age":74,"country":"Venezuela","phone":"5848226578"},
{"id":170,"first_name":"Bernardine","last_name":"Bonhome","email":"bbonhome4p@examiner.com","date_of_birth":"2012-11-26T02:55:48Z","age":26,"country":"Peru","phone":"4989424085"},
{"id":171,"first_name":"Aloin","last_name":"Orcott","email":"aorcott4q@typepad.com","date_of_birth":"2011-01-12T03:39:09Z","age":56,"country":"Afghanistan","phone":"6131114533"},
{"id":172,"first_name":"Cliff","last_name":"Macourek","email":"cmacourek4r@marketwatch.com","date_of_birth":"2011-05-26T08:24:09Z","age":22,"country":"Russia","phone":"5664656059"},
{"id":173,"first_name":"Elene","last_name":"Prosch","email":"eprosch4s@yale.edu","date_of_birth":"2000-12-13T20:55:59Z","age":36,"country":"Portugal","phone":"2587635998"},
{"id":174,"first_name":"Lucine","last_name":"Bulmer","email":"lbulmer4t@pagesperso-orange.fr","date_of_birth":"1996-06-29T06:58:57Z","age":57,"country":"China","phone":"8673261942"},
{"id":175,"first_name":"Megen","last_name":"Bome","email":"mbome4u@wordpress.com","date_of_birth":"1994-09-16T18:53:57Z","age":68,"country":"Netherlands","phone":"4082870471"},
{"id":176,"first_name":"Donavon","last_name":"Ludman","email":"dludman4v@ezinearticles.com","date_of_birth":"1993-05-17T12:30:43Z","age":35,"country":"Poland","phone":"1552761983"},
{"id":177,"first_name":"Waite","last_name":"Phayre","email":"wphayre4w@ucoz.ru","date_of_birth":"2007-05-02T05:14:13Z","age":59,"country":"South Africa","phone":"1782921228"},
{"id":178,"first_name":"Carrie","last_name":"Twells","email":"ctwells4x@sun.com","date_of_birth":"2003-06-18T15:17:32Z","age":54,"country":"Madagascar","phone":"2881346710"},
{"id":179,"first_name":"Rica","last_name":"Will","email":"rwill4y@symantec.com","date_of_birth":"1989-07-24T07:47:00Z","age":37,"country":"Russia","phone":"8363129374"},
{"id":180,"first_name":"Lia","last_name":"Heimes","email":"lheimes4z@state.tx.us","date_of_birth":"1982-03-15T11:40:18Z","age":65,"country":"Indonesia","phone":"4386819541"},
{"id":181,"first_name":"Tanney","last_name":"Glaze","email":"tglaze50@printfriendly.com","date_of_birth":"2011-07-01T08:32:40Z","age":51,"country":"Russia","phone":"4667289989"},
{"id":182,"first_name":"Vickie","last_name":"Roseby","email":"vroseby51@addthis.com","date_of_birth":"1996-03-13T16:40:17Z","age":53,"country":"Peru","phone":"7645631235"},
{"id":183,"first_name":"Alano","last_name":"Irce","email":"airce52@youku.com","date_of_birth":"2017-04-20T18:47:34Z","age":38,"country":"France","phone":"4755641540"},
{"id":184,"first_name":"Nealson","last_name":"Bumpus","email":"nbumpus53@accuweather.com","date_of_birth":"1980-06-28T21:36:39Z","age":36,"country":"Brazil","phone":"5556255386"},
{"id":185,"first_name":"Bonnibelle","last_name":"Glide","email":"bglide54@alibaba.com","date_of_birth":"1984-02-23T12:03:16Z","age":28,"country":"Portugal","phone":"9542413410"},
{"id":186,"first_name":"Kara","last_name":"Menat","email":"kmenat55@wikimedia.org","date_of_birth":"2004-12-05T14:04:31Z","age":40,"country":"Canada","phone":"7593961368"},
{"id":187,"first_name":"Joya","last_name":"Bowerbank","email":"jbowerbank56@nyu.edu","date_of_birth":"1973-06-25T08:26:34Z","age":29,"country":"United States","phone":"9163959397"},
{"id":188,"first_name":"Berna","last_name":"Tipper","email":"btipper57@hatena.ne.jp","date_of_birth":"1995-01-18T16:52:52Z","age":72,"country":"Indonesia","phone":"8766719286"},
{"id":189,"first_name":"Bobine","last_name":"Mounsey","email":"bmounsey58@mysql.com","date_of_birth":"1979-10-03T19:57:53Z","age":71,"country":"China","phone":"9609989173"},
{"id":190,"first_name":"Lara","last_name":"Rosenblum","email":"lrosenblum59@paginegialle.it","date_of_birth":"2000-03-19T07:10:00Z","age":25,"country":"Thailand","phone":"8023912631"},
{"id":191,"first_name":"Carolus","last_name":"Herrieven","email":"cherrieven5a@flavors.me","date_of_birth":"1984-06-14T13:40:27Z","age":33,"country":"Portugal","phone":"5026916528"},
{"id":192,"first_name":"Torrin","last_name":"Hounihan","email":"thounihan5b@e-recht24.de","date_of_birth":"2004-04-06T13:37:40Z","age":67,"country":"Greece","phone":"2505962195"},
{"id":193,"first_name":"Jae","last_name":"Petyanin","email":"jpetyanin5c@thetimes.co.uk","date_of_birth":"1980-10-28T13:40:33Z","age":40,"country":"China","phone":"7985713804"},
{"id":194,"first_name":"Ximenes","last_name":"Meiklejohn","email":"xmeiklejohn5d@theatlantic.com","date_of_birth":"2005-03-01T00:28:47Z","age":27,"country":"Nicaragua","phone":"9398244314"},
{"id":195,"first_name":"Ondrea","last_name":"Minico","email":"ominico5e@craigslist.org","date_of_birth":"2010-10-27T19:48:02Z","age":30,"country":"Indonesia","phone":"4004957381"},
{"id":196,"first_name":"Jemie","last_name":"Bleeze","email":"jbleeze5f@moonfruit.com","date_of_birth":"1990-04-05T13:58:24Z","age":60,"country":"China","phone":"7016874866"},
{"id":197,"first_name":"Halsy","last_name":"Toplis","email":"htoplis5g@tripadvisor.com","date_of_birth":"1971-07-13T10:26:35Z","age":58,"country":"China","phone":"2757356318"},
{"id":198,"first_name":"Marsiella","last_name":"Lardge","email":"mlardge5h@qq.com","date_of_birth":"2017-03-21T07:35:12Z","age":71,"country":"Mexico","phone":"6732540466"},
{"id":199,"first_name":"Carole","last_name":"Tungay","email":"ctungay5i@uiuc.edu","date_of_birth":"1973-05-14T03:42:47Z","age":30,"country":"Bolivia","phone":"3414469990"},
{"id":200,"first_name":"Bambie","last_name":"Kellart","email":"bkellart5j@bloglines.com","date_of_birth":"2004-09-04T16:48:04Z","age":72,"country":"Mexico","phone":"2229487413"}]